{
	"add": {
		"doc": {
			"id": "11f1db7d6c4d5d692e843fc5705c5b4c46b4d66cf1b76dcc6fdc4f870a68708d",
			"url": "https://upload.wikimedia.org/wikipedia/commons/thumb/c/cf/Sunset%2C_UCR.jpg/220px-Sunset%2C_UCR.jpg",
			"previous": " ",
			"after": " UCR s residence halls consist of three structures Aberdeen Inverness Lothian and Pentland Hills which as of 2002 housed 2 930 students in triple double and single rooms In addition UCR features several on campus apartment complexes such as Stonehaven Bannockburn Village University Plaza Falkirk Oban Glen Mor and International Village which together house 959 students UCR also offers student family housing at Canyon Crest a low density residential community that serves 268 and is slated for demolition to make room for higher density residence halls 31 Glen Mor an apartment housing complex adjacent to Pentland Hills was opened in 2007 and the university also purchased a nearby apartment complex which is now known as Falkirk for student housing in 2007 96 About half of the student population lives in off campus apartments one fourth commute and one fourth live on campus 96 Thirty percent of students remain on campus for the weekend 97 ",
			"color": "plum|0.62788 black|0.27585 rosy|0.043148 brown|0.043148  ",
			"after_weights": " UCR|1 s|0.99351 residence|0.98701 halls|0.98052 consist|0.97403 of|0.96753 three|0.96104 structures|0.95455 Aberdeen|0.94805 Inverness|0.94156 Lothian|0.93506 and|0.92857 Pentland|0.92208 Hills|0.91558 which|0.90909 as|0.9026 of|0.8961 2002|0.88961 housed|0.88312 2|0.87662 930|0.87013 students|0.86364 in|0.85714 triple|0.85065 double|0.84416 and|0.83766 single|0.83117 rooms|0.82468 In|0.81818 addition|0.81169 UCR|0.80519 features|0.7987 several|0.79221 on|0.78571 campus|0.77922 apartment|0.77273 complexes|0.76623 such|0.75974 as|0.75325 Stonehaven|0.74675 Bannockburn|0.74026 Village|0.73377 University|0.72727 Plaza|0.72078 Falkirk|0.71429 Oban|0.70779 Glen|0.7013 Mor|0.69481 and|0.68831 International|0.68182 Village|0.67532 which|0.66883 together|0.66234 house|0.65584 959|0.64935 students|0.64286 UCR|0.63636 also|0.62987 offers|0.62338 student|0.61688 family|0.61039 housing|0.6039 at|0.5974 Canyon|0.59091 Crest|0.58442 a|0.57792 low|0.57143 density|0.56494 residential|0.55844 community|0.55195 that|0.54545 serves|0.53896 268|0.53247 and|0.52597 is|0.51948 slated|0.51299 for|0.50649 demolition|0.5 to|0.49351 make|0.48701 room|0.48052 for|0.47403 higher|0.46753 density|0.46104 residence|0.45455 halls|0.44805 31|0.44156 Glen|0.43506 Mor|0.42857 an|0.42208 apartment|0.41558 housing|0.40909 complex|0.4026 adjacent|0.3961 to|0.38961 Pentland|0.38312 Hills|0.37662 was|0.37013 opened|0.36364 in|0.35714 2007|0.35065 and|0.34416 the|0.33766 university|0.33117 also|0.32468 purchased|0.31818 a|0.31169 nearby|0.30519 apartment|0.2987 complex|0.29221 which|0.28571 is|0.27922 now|0.27273 known|0.26623 as|0.25974 Falkirk|0.25325 for|0.24675 student|0.24026 housing|0.23377 in|0.22727 2007|0.22078 96|0.21429 About|0.20779 half|0.2013 of|0.19481 the|0.18831 student|0.18182 population|0.17532 lives|0.16883 in|0.16234 off|0.15584 campus|0.14935 apartments|0.14286 one|0.13636 fourth|0.12987 commute|0.12338 and|0.11688 one|0.11039 fourth|0.1039 live|0.097403 on|0.090909 campus|0.084416 96|0.077922 Thirty|0.071429 percent|0.064935 of|0.058442 students|0.051948 remain|0.045455 on|0.038961 campus|0.032468 for|0.025974 the|0.019481 weekend|0.012987 97|0.0064935 |0",
			"previous_weights": " "
		}
	}
}
