{
	"add": {
		"doc": {
			"id": "134d6a7be1cc168cf558c8ee339e3d826b8ee60f53cd20898b7da41ebcf89931",
			"url": "https://upload.wikimedia.org/wikipedia/commons/thumb/4/4d/Defense.gov_News_Photo_010917-D-9880W-034.jpg/220px-Defense.gov_News_Photo_010917-D-9880W-034.jpg",
			"previous": " ",
			"after": " Though Bush originally outlined an ambitious domestic agenda his priorities were significantly altered following the September 11 terrorist attacks in 2001 100 Wars were waged in Afghanistan and Iraq with significant domestic debates regarding immigration healthcare Social Security economic policy and treatment of terrorist detainees Over an eight year period Bush s once high approval ratings 101 steadily declined while his disapproval numbers increased significantly 102 In 2007 the United States entered the longest post World War II recession 103 ",
			"color": "black|0.65552 light|0.030887 steel|0.030887 blue|0.030887 brown|0.026948 dark|0.024069 salmon|0.024069 light|0.017175 slate|0.017175 gray|0.017175 lavender|0.017173 dim|0.015736 gray|0.015736 dim|0.015736 grey|0.015736 slate|0.014744 gray|0.014744 firebrick|0.013895 dark|0.012456 gray|0.012456 dark|0.012456 grey|0.012456 alice|0.010342 blue|0.010342 silver|0.010225 gray|0.0096379 grey|0.0096379 ghost|0.0095908 white|0.0095908 lavender|0.0094637 blush|0.0094637 light|0.0091468 gray|0.0091468 light|0.0091468 grey|0.0091468 white|0.0087565 smoke|0.0087565 gainsboro|0.0084762 snow|0.007208 azure|0.0072029 white|0.0068952 rosy|0.0067862 brown|0.0067862 misty|0.0066333 rose|0.0066333 dark|0.0064974 slate|0.0064974 gray|0.0064974 mint|0.0061513 cream|0.0061513 light|0.00566 blue|0.00566 light|0.0055397 coral|0.0055397 sea|0.0051881 shell|0.0051881 thistle|0.0050728  ",
			"after_weights": " Though|1 Bush|0.9875 originally|0.975 outlined|0.9625 an|0.95 ambitious|0.9375 domestic|0.925 agenda|0.9125 his|0.9 priorities|0.8875 were|0.875 significantly|0.8625 altered|0.85 following|0.8375 the|0.825 September|0.8125 11|0.8 terrorist|0.7875 attacks|0.775 in|0.7625 2001|0.75 100|0.7375 Wars|0.725 were|0.7125 waged|0.7 in|0.6875 Afghanistan|0.675 and|0.6625 Iraq|0.65 with|0.6375 significant|0.625 domestic|0.6125 debates|0.6 regarding|0.5875 immigration|0.575 healthcare|0.5625 Social|0.55 Security|0.5375 economic|0.525 policy|0.5125 and|0.5 treatment|0.4875 of|0.475 terrorist|0.4625 detainees|0.45 Over|0.4375 an|0.425 eight|0.4125 year|0.4 period|0.3875 Bush|0.375 s|0.3625 once|0.35 high|0.3375 approval|0.325 ratings|0.3125 101|0.3 steadily|0.2875 declined|0.275 while|0.2625 his|0.25 disapproval|0.2375 numbers|0.225 increased|0.2125 significantly|0.2 102|0.1875 In|0.175 2007|0.1625 the|0.15 United|0.1375 States|0.125 entered|0.1125 the|0.1 longest|0.0875 post|0.075 World|0.0625 War|0.05 II|0.0375 recession|0.025 103|0.0125 |0",
			"previous_weights": " "
		}
	}
}
