{
	"add": {
		"doc": {
			"id": "14721b3170e6ea7c234435499af12f8686fbae17d2fe74b19676be0fad4e8978",
			"url": "https://upload.wikimedia.org/wikipedia/commons/thumb/3/3a/Air_Labrador_Beech_1900D.jpg/220px-Air_Labrador_Beech_1900D.jpg",
			"previous": " On December 26 2013 Textron agreed to purchase Beechcraft including the discontinued Hawker jet line for 1 4 billion The sale was expected to be concluded in the first half of 2014 pending government approval Textron CEO Scott Donnelly indicated that Beechcraft and Cessna would be combined to form a new light aircraft manufacturing concern that will result in US 65M 85M in annual savings over keeping the companies separate 8 9 10 11 Textron s initial plan is to keep both Beechcraft and Cessna as separate brands 12 ",
			"after": " ",
			"color": "light|0.89072 steel|0.89072 blue|0.89072 sky|0.022533 blue|0.022533 black|0.019782 light|0.010769 blue|0.010769 dim|0.0089227 gray|0.0089227 dim|0.0089227 grey|0.0089227 light|0.0074031 slate|0.0074031 gray|0.0074031 slate|0.0072442 gray|0.0072442 dark|0.0045891 gray|0.0045891 dark|0.0045891 grey|0.0045891 steel|0.004559 blue|0.004559  ",
			"after_weights": " ",
			"previous_weights": " On|0 December|0.011236 26|0.022472 2013|0.033708 Textron|0.044944 agreed|0.05618 to|0.067416 purchase|0.078652 Beechcraft|0.089888 including|0.10112 the|0.11236 discontinued|0.1236 Hawker|0.13483 jet|0.14607 line|0.1573 for|0.16854 1|0.17978 4|0.19101 billion|0.20225 The|0.21348 sale|0.22472 was|0.23596 expected|0.24719 to|0.25843 be|0.26966 concluded|0.2809 in|0.29213 the|0.30337 first|0.31461 half|0.32584 of|0.33708 2014|0.34831 pending|0.35955 government|0.37079 approval|0.38202 Textron|0.39326 CEO|0.40449 Scott|0.41573 Donnelly|0.42697 indicated|0.4382 that|0.44944 Beechcraft|0.46067 and|0.47191 Cessna|0.48315 would|0.49438 be|0.50562 combined|0.51685 to|0.52809 form|0.53933 a|0.55056 new|0.5618 light|0.57303 aircraft|0.58427 manufacturing|0.59551 concern|0.60674 that|0.61798 will|0.62921 result|0.64045 in|0.65169 US|0.66292 65M|0.67416 85M|0.68539 in|0.69663 annual|0.70787 savings|0.7191 over|0.73034 keeping|0.74157 the|0.75281 companies|0.76404 separate|0.77528 8|0.78652 9|0.79775 10|0.80899 11|0.82022 Textron|0.83146 s|0.8427 initial|0.85393 plan|0.86517 is|0.8764 to|0.88764 keep|0.89888 both|0.91011 Beechcraft|0.92135 and|0.93258 Cessna|0.94382 as|0.95506 separate|0.96629 brands|0.97753 12|0.98876 |1"
		}
	}
}
