{
	"add": {
		"doc": {
			"id": "2399a766f0961901bc4aa57e5979adf729426573392f93c894e609dcfa5f80e0",
			"url": "https://upload.wikimedia.org/wikipedia/commons/thumb/5/5f/Millennium_Dome.jpg/90px-Millennium_Dome.jpg",
			"previous": " Portal Technology Selected articles 28",
			"after": " Buro Happold is a professional services firm providing engineering consultancy design planning project management and consulting services for all aspects of buildings infrastructure and the environment with its head office in Bath Somerset It was founded in 1976 by Sir Edmund Happold in Bath in the southwest of England when he left Ove Arup and Partners to take up a post at the University of Bath as Professor of Architecture and Engineering Design Originally working mainly on projects in the Middle East the firm now operates worldwide and in almost all areas of engineering for the built environment with offices in seven countries The parent company owns the subsidiary companies Happold Consulting Happold Media and Happold Safe and Secure The firm includes a number of specialist engineering consultancy groups including fire engineering and lighting consultancy ",
			"color": "light|0.20447 steel|0.20447 blue|0.20447 black|0.13389 light|0.088366 blue|0.088366 slate|0.063801 gray|0.063801 burly|0.057688 wood|0.057688 light|0.049296 gray|0.049296 light|0.049296 grey|0.049296 tan|0.045143 gainsboro|0.036083 dim|0.035721 gray|0.035721 dim|0.035721 grey|0.035721 gray|0.031423 grey|0.031423 light|0.027224 slate|0.027224 gray|0.027224 powder|0.023349 blue|0.023349 silver|0.021293 wheat|0.019232 navajo|0.01588 white|0.01588 orange|0.011732 sandy|0.010568 brown|0.010568 moccasin|0.01026 light|0.010108 sky|0.010108 blue|0.010108 lavender|0.0096407 peru|0.008756 saddle|0.0085404 brown|0.0085404 dark|0.0082816 orange|0.0082816 peach|0.0079078 puff|0.0079078  ",
			"after_weights": " Buro|1 Happold|0.99259 is|0.98519 a|0.97778 professional|0.97037 services|0.96296 firm|0.95556 providing|0.94815 engineering|0.94074 consultancy|0.93333 design|0.92593 planning|0.91852 project|0.91111 management|0.9037 and|0.8963 consulting|0.88889 services|0.88148 for|0.87407 all|0.86667 aspects|0.85926 of|0.85185 buildings|0.84444 infrastructure|0.83704 and|0.82963 the|0.82222 environment|0.81481 with|0.80741 its|0.8 head|0.79259 office|0.78519 in|0.77778 Bath|0.77037 Somerset|0.76296 It|0.75556 was|0.74815 founded|0.74074 in|0.73333 1976|0.72593 by|0.71852 Sir|0.71111 Edmund|0.7037 Happold|0.6963 in|0.68889 Bath|0.68148 in|0.67407 the|0.66667 southwest|0.65926 of|0.65185 England|0.64444 when|0.63704 he|0.62963 left|0.62222 Ove|0.61481 Arup|0.60741 and|0.6 Partners|0.59259 to|0.58519 take|0.57778 up|0.57037 a|0.56296 post|0.55556 at|0.54815 the|0.54074 University|0.53333 of|0.52593 Bath|0.51852 as|0.51111 Professor|0.5037 of|0.4963 Architecture|0.48889 and|0.48148 Engineering|0.47407 Design|0.46667 Originally|0.45926 working|0.45185 mainly|0.44444 on|0.43704 projects|0.42963 in|0.42222 the|0.41481 Middle|0.40741 East|0.4 the|0.39259 firm|0.38519 now|0.37778 operates|0.37037 worldwide|0.36296 and|0.35556 in|0.34815 almost|0.34074 all|0.33333 areas|0.32593 of|0.31852 engineering|0.31111 for|0.3037 the|0.2963 built|0.28889 environment|0.28148 with|0.27407 offices|0.26667 in|0.25926 seven|0.25185 countries|0.24444 The|0.23704 parent|0.22963 company|0.22222 owns|0.21481 the|0.20741 subsidiary|0.2 companies|0.19259 Happold|0.18519 Consulting|0.17778 Happold|0.17037 Media|0.16296 and|0.15556 Happold|0.14815 Safe|0.14074 and|0.13333 Secure|0.12593 The|0.11852 firm|0.11111 includes|0.1037 a|0.096296 number|0.088889 of|0.081481 specialist|0.074074 engineering|0.066667 consultancy|0.059259 groups|0.051852 including|0.044444 fire|0.037037 engineering|0.02963 and|0.022222 lighting|0.014815 consultancy|0.0074074 |0",
			"previous_weights": " Portal|0 Technology|0.25 Selected|0.5 articles|0.75 28|1"
		}
	}
}
