{
	"add": {
		"doc": {
			"id": "4d9fe289e0b49b6a01ab35c9737a6a8f63d080b32b01cd54230c39c3ca1892ef",
			"url": "https://upload.wikimedia.org/wikipedia/commons/thumb/7/7e/Carisbrook.jpg/220px-Carisbrook.jpg",
			"previous": " ",
			"after": " Carisbrook the city s former main rugby union venue and a former Test cricket ground is at the eastern end of the suburb between The Glen and the Hillside Railway Workshops 51 It was the home of Otago Rugby Union until a new stadium opened in North Dunedin the Forsyth Barr Stadium at University Plaza in 2011 The new stadium is the new home of the Otago Rugby Union and Highlanders Super Rugby franchise and met with some opposition within Dunedin with objections focusing largely on the cost 52 The future of Carisbrook looks bleak and many of the former facilities are in the process of being dismantled or removed ",
			"color": "black|0.20243 dim|0.13331 gray|0.13331 dim|0.13331 grey|0.13331 gray|0.093239 grey|0.093239 dark|0.088287 gray|0.088287 dark|0.088287 grey|0.088287 light|0.063266 slate|0.063266 gray|0.063266 dark|0.053335 slate|0.053335 gray|0.053335 slate|0.052109 gray|0.052109 silver|0.052075 rosy|0.034114 brown|0.034114 thistle|0.033192 light|0.030346 gray|0.030346 light|0.030346 grey|0.030346 light|0.02439 steel|0.02439 blue|0.02439 gainsboro|0.021302 misty|0.013155 rose|0.013155 lavender|0.012405 lavender|0.011672 blush|0.011672  ",
			"after_weights": " Carisbrook|1 the|0.99091 city|0.98182 s|0.97273 former|0.96364 main|0.95455 rugby|0.94545 union|0.93636 venue|0.92727 and|0.91818 a|0.90909 former|0.9 Test|0.89091 cricket|0.88182 ground|0.87273 is|0.86364 at|0.85455 the|0.84545 eastern|0.83636 end|0.82727 of|0.81818 the|0.80909 suburb|0.8 between|0.79091 The|0.78182 Glen|0.77273 and|0.76364 the|0.75455 Hillside|0.74545 Railway|0.73636 Workshops|0.72727 51|0.71818 It|0.70909 was|0.7 the|0.69091 home|0.68182 of|0.67273 Otago|0.66364 Rugby|0.65455 Union|0.64545 until|0.63636 a|0.62727 new|0.61818 stadium|0.60909 opened|0.6 in|0.59091 North|0.58182 Dunedin|0.57273 the|0.56364 Forsyth|0.55455 Barr|0.54545 Stadium|0.53636 at|0.52727 University|0.51818 Plaza|0.50909 in|0.5 2011|0.49091 The|0.48182 new|0.47273 stadium|0.46364 is|0.45455 the|0.44545 new|0.43636 home|0.42727 of|0.41818 the|0.40909 Otago|0.4 Rugby|0.39091 Union|0.38182 and|0.37273 Highlanders|0.36364 Super|0.35455 Rugby|0.34545 franchise|0.33636 and|0.32727 met|0.31818 with|0.30909 some|0.3 opposition|0.29091 within|0.28182 Dunedin|0.27273 with|0.26364 objections|0.25455 focusing|0.24545 largely|0.23636 on|0.22727 the|0.21818 cost|0.20909 52|0.2 The|0.19091 future|0.18182 of|0.17273 Carisbrook|0.16364 looks|0.15455 bleak|0.14545 and|0.13636 many|0.12727 of|0.11818 the|0.10909 former|0.1 facilities|0.090909 are|0.081818 in|0.072727 the|0.063636 process|0.054545 of|0.045455 being|0.036364 dismantled|0.027273 or|0.018182 removed|0.0090909 |0",
			"previous_weights": " "
		}
	}
}
