{
	"add": {
		"doc": {
			"id": "718cb1e2cbc8e302f85e49fbb2dc5cdc19a28181e2654c6b9164dc2dc43a933e",
			"url": "https://upload.wikimedia.org/math/5/d/0/5d0fd78a32afdffc478204baf1cb19bb.png",
			"previous": " To find the length of for example February 2000 the calculation is d 30  The algorithm utilises the integral or floor function thus is that part of the number x which lies to the left of the decimal point It is only necessary to work through the complete function when calculating the length of February in a year which is divisible by 100 without remainder When calculating the length of February in any other year it is only necessary to evaluate the terms to the left of the fifth sign When calculating the length of any other month it is only necessary to evaluate the terms to the left of the third sign ",
			"after": "  The origins of English naming used by the Gregorian calendar ",
			"color": "dim|0.28048 gray|0.28048 dim|0.28048 grey|0.28048 gray|0.23754 grey|0.23754 dark|0.22728 gray|0.22728 dark|0.22728 grey|0.22728 black|0.15952 silver|0.07757 light|0.015285 gray|0.015285 light|0.015285 grey|0.015285  ",
			"after_weights": " |1 The|0.90909 origins|0.81818 of|0.72727 English|0.63636 naming|0.54545 used|0.45455 by|0.36364 the|0.27273 Gregorian|0.18182 calendar|0.090909 |0",
			"previous_weights": " To|0 find|0.0087719 the|0.017544 length|0.026316 of|0.035088 for|0.04386 example|0.052632 February|0.061404 2000|0.070175 the|0.078947 calculation|0.087719 is|0.096491 d|0.10526 30|0.11404 |0.12281 The|0.13158 algorithm|0.14035 utilises|0.14912 the|0.15789 integral|0.16667 or|0.17544 floor|0.18421 function|0.19298 thus|0.20175 is|0.21053 that|0.2193 part|0.22807 of|0.23684 the|0.24561 number|0.25439 x|0.26316 which|0.27193 lies|0.2807 to|0.28947 the|0.29825 left|0.30702 of|0.31579 the|0.32456 decimal|0.33333 point|0.34211 It|0.35088 is|0.35965 only|0.36842 necessary|0.37719 to|0.38596 work|0.39474 through|0.40351 the|0.41228 complete|0.42105 function|0.42982 when|0.4386 calculating|0.44737 the|0.45614 length|0.46491 of|0.47368 February|0.48246 in|0.49123 a|0.5 year|0.50877 which|0.51754 is|0.52632 divisible|0.53509 by|0.54386 100|0.55263 without|0.5614 remainder|0.57018 When|0.57895 calculating|0.58772 the|0.59649 length|0.60526 of|0.61404 February|0.62281 in|0.63158 any|0.64035 other|0.64912 year|0.65789 it|0.66667 is|0.67544 only|0.68421 necessary|0.69298 to|0.70175 evaluate|0.71053 the|0.7193 terms|0.72807 to|0.73684 the|0.74561 left|0.75439 of|0.76316 the|0.77193 fifth|0.7807 sign|0.78947 When|0.79825 calculating|0.80702 the|0.81579 length|0.82456 of|0.83333 any|0.84211 other|0.85088 month|0.85965 it|0.86842 is|0.87719 only|0.88596 necessary|0.89474 to|0.90351 evaluate|0.91228 the|0.92105 terms|0.92982 to|0.9386 the|0.94737 left|0.95614 of|0.96491 the|0.97368 third|0.98246 sign|0.99123 |1"
		}
	}
}
