{
	"add": {
		"doc": {
			"id": "7b0816b47141c693586070e12d09d108eb4b9afbb09762bf0f6967457511dcfe",
			"url": "https://upload.wikimedia.org/math/e/5/9/e59608faa861c9ddc00f6541c7bfdb1d.png",
			"previous": " Thales theorem named after Thales of Miletus states that if A B and C are points on a circle where the line AC is a diameter of the circle then the angle ABC is a right angle Cantor supposed that Thales proved his theorem by means of Euclid Book I Prop 32 after the manner of Euclid Book III Prop 31 16 Tradition has it that Thales sacrificed an ox to celebrate this theorem 17 ",
			"after": " ",
			"color": "dim|0.40377 gray|0.40377 dim|0.40377 grey|0.40377 gray|0.28446 grey|0.28446 dark|0.17313 gray|0.17313 dark|0.17313 grey|0.17313 silver|0.070432 light|0.033126 gray|0.033126 light|0.033126 grey|0.033126 gainsboro|0.022447 white|0.0036581 smoke|0.0036581  ",
			"after_weights": " ",
			"previous_weights": " Thales|0 theorem|0.013333 named|0.026667 after|0.04 Thales|0.053333 of|0.066667 Miletus|0.08 states|0.093333 that|0.10667 if|0.12 A|0.13333 B|0.14667 and|0.16 C|0.17333 are|0.18667 points|0.2 on|0.21333 a|0.22667 circle|0.24 where|0.25333 the|0.26667 line|0.28 AC|0.29333 is|0.30667 a|0.32 diameter|0.33333 of|0.34667 the|0.36 circle|0.37333 then|0.38667 the|0.4 angle|0.41333 ABC|0.42667 is|0.44 a|0.45333 right|0.46667 angle|0.48 Cantor|0.49333 supposed|0.50667 that|0.52 Thales|0.53333 proved|0.54667 his|0.56 theorem|0.57333 by|0.58667 means|0.6 of|0.61333 Euclid|0.62667 Book|0.64 I|0.65333 Prop|0.66667 32|0.68 after|0.69333 the|0.70667 manner|0.72 of|0.73333 Euclid|0.74667 Book|0.76 III|0.77333 Prop|0.78667 31|0.8 16|0.81333 Tradition|0.82667 has|0.84 it|0.85333 that|0.86667 Thales|0.88 sacrificed|0.89333 an|0.90667 ox|0.92 to|0.93333 celebrate|0.94667 this|0.96 theorem|0.97333 17|0.98667 |1"
		}
	}
}
