{
	"add": {
		"doc": {
			"id": "964b76518758df6d79d346e25f61339c7720202c788f6d36c25b2bce3e04075f",
			"url": "https://upload.wikimedia.org/wikipedia/commons/thumb/9/96/Beginning_Iliad.svg/300px-Beginning_Iliad.svg.png",
			"previous": " ",
			"after": " Poetry is a form of literature that uses aesthetic and rhythmic qualities of language such as phonaesthetics sound symbolism and metre to evoke meanings in addition to or in place of the prosaic ostensible meaning ",
			"after_weights": " Poetry|1 is|0.97143 a|0.94286 form|0.91429 of|0.88571 literature|0.85714 that|0.82857 uses|0.8 aesthetic|0.77143 and|0.74286 rhythmic|0.71429 qualities|0.68571 of|0.65714 language|0.62857 such|0.6 as|0.57143 phonaesthetics|0.54286 sound|0.51429 symbolism|0.48571 and|0.45714 metre|0.42857 to|0.4 evoke|0.37143 meanings|0.34286 in|0.31429 addition|0.28571 to|0.25714 or|0.22857 in|0.2 place|0.17143 of|0.14286 the|0.11429 prosaic|0.085714 ostensible|0.057143 meaning|0.028571 |0",
			"previous_weights": " "
		}
	}
}
