{
	"add": {
		"doc": {
			"id": "b0d65db550764ea0861a8e1150ce42bc591907ba2c9bcc4035af4610107e0f59",
			"url": "https://upload.wikimedia.org/wikipedia/en/thumb/9/9e/Geekipedia.jpg/220px-Geekipedia.jpg",
			"previous": " From 2004 to 2008 Wired organized an annual festival of innovative products and technologies 27 A NextFest had also been planned for 2009 but it was later canceled 28 ",
			"after": " Wired s writers have included Jorn Barger John Perry Barlow John Battelle Paul Boutin Stewart Brand Gareth Branwyn Po Bronson Scott Carney Michael Chorost Douglas Coupland James Daly Joshua Davis J Bradford DeLong Mark Dery David Diamond Cory Doctorow Esther Dyson Mark Frauenfelder Simson Garfinkel William Gibson Dan Gillmor Mike Godwin George Gilder Lou Ann Hammond Chris Hardwick Danny Hillis Steven Johnson Bill Joy Jon Katz Leander Kahney Richard Kadrey Jaron Lanier Lawrence Lessig Paul Levinson Steven Levy John Markoff Wil McCarthy Russ Mitchell Glyn Moody Charles Platt Josh Quittner Spencer Reiss Howard Rheingold Rudy Rucker Paul Saffo Adam Savage Evan Schwartz Peter Schwartz Alex Steffen Neal Stephenson Bruce Sterling John Hodgman Kevin Warwick Dave Winer Belinda Parmar and Gary Wolf ",
			"after_weights": " Wired|1 s|0.99174 writers|0.98347 have|0.97521 included|0.96694 Jorn|0.95868 Barger|0.95041 John|0.94215 Perry|0.93388 Barlow|0.92562 John|0.91736 Battelle|0.90909 Paul|0.90083 Boutin|0.89256 Stewart|0.8843 Brand|0.87603 Gareth|0.86777 Branwyn|0.8595 Po|0.85124 Bronson|0.84298 Scott|0.83471 Carney|0.82645 Michael|0.81818 Chorost|0.80992 Douglas|0.80165 Coupland|0.79339 James|0.78512 Daly|0.77686 Joshua|0.7686 Davis|0.76033 J|0.75207 Bradford|0.7438 DeLong|0.73554 Mark|0.72727 Dery|0.71901 David|0.71074 Diamond|0.70248 Cory|0.69421 Doctorow|0.68595 Esther|0.67769 Dyson|0.66942 Mark|0.66116 Frauenfelder|0.65289 Simson|0.64463 Garfinkel|0.63636 William|0.6281 Gibson|0.61983 Dan|0.61157 Gillmor|0.60331 Mike|0.59504 Godwin|0.58678 George|0.57851 Gilder|0.57025 Lou|0.56198 Ann|0.55372 Hammond|0.54545 Chris|0.53719 Hardwick|0.52893 Danny|0.52066 Hillis|0.5124 Steven|0.50413 Johnson|0.49587 Bill|0.4876 Joy|0.47934 Jon|0.47107 Katz|0.46281 Leander|0.45455 Kahney|0.44628 Richard|0.43802 Kadrey|0.42975 Jaron|0.42149 Lanier|0.41322 Lawrence|0.40496 Lessig|0.39669 Paul|0.38843 Levinson|0.38017 Steven|0.3719 Levy|0.36364 John|0.35537 Markoff|0.34711 Wil|0.33884 McCarthy|0.33058 Russ|0.32231 Mitchell|0.31405 Glyn|0.30579 Moody|0.29752 Charles|0.28926 Platt|0.28099 Josh|0.27273 Quittner|0.26446 Spencer|0.2562 Reiss|0.24793 Howard|0.23967 Rheingold|0.2314 Rudy|0.22314 Rucker|0.21488 Paul|0.20661 Saffo|0.19835 Adam|0.19008 Savage|0.18182 Evan|0.17355 Schwartz|0.16529 Peter|0.15702 Schwartz|0.14876 Alex|0.1405 Steffen|0.13223 Neal|0.12397 Stephenson|0.1157 Bruce|0.10744 Sterling|0.099174 John|0.090909 Hodgman|0.082645 Kevin|0.07438 Warwick|0.066116 Dave|0.057851 Winer|0.049587 Belinda|0.041322 Parmar|0.033058 and|0.024793 Gary|0.016529 Wolf|0.0082645 |0",
			"previous_weights": " From|0 2004|0.034483 to|0.068966 2008|0.10345 Wired|0.13793 organized|0.17241 an|0.2069 annual|0.24138 festival|0.27586 of|0.31034 innovative|0.34483 products|0.37931 and|0.41379 technologies|0.44828 27|0.48276 A|0.51724 NextFest|0.55172 had|0.58621 also|0.62069 been|0.65517 planned|0.68966 for|0.72414 2009|0.75862 but|0.7931 it|0.82759 was|0.86207 later|0.89655 canceled|0.93103 28|0.96552 |1"
		}
	}
}
