{
	"add": {
		"doc": {
			"id": "beb9db97c42d9a411131459454ace2a9fa56268985455f0ee7c9f91376322a95",
			"url": "https://upload.wikimedia.org/wikipedia/commons/thumb/d/de/BLU-26_cluster_sub-munition.JPG/220px-BLU-26_cluster_sub-munition.JPG",
			"previous": " ",
			"after": " Twenty two years following the end of the Laotian War on 15 May 1997 the U S officially acknowledged its role in the Secret War A memorial to honor of American and Hmong contributions to U S air and ground combat efforts during the conflict was established by the Lao Veterans of America the Center for Public Policy Analysis in cooperation with the US Congress and others The Laos Memorial is located on the grounds of the Arlington National Cemetery between the John F Kennedy Eternal Flame and the Tomb of the Unknown Soldier ",
			"after_weights": " Twenty|1 two|0.98936 years|0.97872 following|0.96809 the|0.95745 end|0.94681 of|0.93617 the|0.92553 Laotian|0.91489 War|0.90426 on|0.89362 15|0.88298 May|0.87234 1997|0.8617 the|0.85106 U|0.84043 S|0.82979 officially|0.81915 acknowledged|0.80851 its|0.79787 role|0.78723 in|0.7766 the|0.76596 Secret|0.75532 War|0.74468 A|0.73404 memorial|0.7234 to|0.71277 honor|0.70213 of|0.69149 American|0.68085 and|0.67021 Hmong|0.65957 contributions|0.64894 to|0.6383 U|0.62766 S|0.61702 air|0.60638 and|0.59574 ground|0.58511 combat|0.57447 efforts|0.56383 during|0.55319 the|0.54255 conflict|0.53191 was|0.52128 established|0.51064 by|0.5 the|0.48936 Lao|0.47872 Veterans|0.46809 of|0.45745 America|0.44681 the|0.43617 Center|0.42553 for|0.41489 Public|0.40426 Policy|0.39362 Analysis|0.38298 in|0.37234 cooperation|0.3617 with|0.35106 the|0.34043 US|0.32979 Congress|0.31915 and|0.30851 others|0.29787 The|0.28723 Laos|0.2766 Memorial|0.26596 is|0.25532 located|0.24468 on|0.23404 the|0.2234 grounds|0.21277 of|0.20213 the|0.19149 Arlington|0.18085 National|0.17021 Cemetery|0.15957 between|0.14894 the|0.1383 John|0.12766 F|0.11702 Kennedy|0.10638 Eternal|0.095745 Flame|0.085106 and|0.074468 the|0.06383 Tomb|0.053191 of|0.042553 the|0.031915 Unknown|0.021277 Soldier|0.010638 |0",
			"previous_weights": " "
		}
	}
}
