{
	"add": {
		"doc": {
			"id": "e298b5fca1e935e85a9354086f7e65b0bd97b114a2791ec0a2756d33c7a18f7f",
			"url": "https://upload.wikimedia.org/wikipedia/commons/thumb/b/bf/Pennsylvania_Academy_of_the_Fine_Arts.jpg/260px-Pennsylvania_Academy_of_the_Fine_Arts.jpg",
			"previous": " Philadelphia has more public art than any other American city 96 In 1872 the Association for Public Art formerly the Fairmount Park Art Association was created the first private association in the United States dedicated to integrating public art and urban planning 97 In 1959 lobbying by the Artists Equity Association helped create the Percent for Art ordinance the first for a U S city 98 The program which has funded more than 200 pieces of public art is administered by the Philadelphia Office of Arts and Culture the city s art agency 99 ",
			"after": " Philadelphia has more murals than any other U S city thanks in part to the 1984 creation of the Department of Recreation s Mural Arts Program which seeks to beautify neighborhoods and provide an outlet for graffiti artists The program has funded more than 2 800 murals by professional staff and volunteer artists and educated more than 20 000 youth in underserved neighborhoods throughout Philadelphia 100 ",
			"after_weights": " Philadelphia|1 has|0.98485 more|0.9697 murals|0.95455 than|0.93939 any|0.92424 other|0.90909 U|0.89394 S|0.87879 city|0.86364 thanks|0.84848 in|0.83333 part|0.81818 to|0.80303 the|0.78788 1984|0.77273 creation|0.75758 of|0.74242 the|0.72727 Department|0.71212 of|0.69697 Recreation|0.68182 s|0.66667 Mural|0.65152 Arts|0.63636 Program|0.62121 which|0.60606 seeks|0.59091 to|0.57576 beautify|0.56061 neighborhoods|0.54545 and|0.5303 provide|0.51515 an|0.5 outlet|0.48485 for|0.4697 graffiti|0.45455 artists|0.43939 The|0.42424 program|0.40909 has|0.39394 funded|0.37879 more|0.36364 than|0.34848 2|0.33333 800|0.31818 murals|0.30303 by|0.28788 professional|0.27273 staff|0.25758 and|0.24242 volunteer|0.22727 artists|0.21212 and|0.19697 educated|0.18182 more|0.16667 than|0.15152 20|0.13636 000|0.12121 youth|0.10606 in|0.090909 underserved|0.075758 neighborhoods|0.060606 throughout|0.045455 Philadelphia|0.030303 100|0.015152 |0",
			"previous_weights": " Philadelphia|0 has|0.010638 more|0.021277 public|0.031915 art|0.042553 than|0.053191 any|0.06383 other|0.074468 American|0.085106 city|0.095745 96|0.10638 In|0.11702 1872|0.12766 the|0.1383 Association|0.14894 for|0.15957 Public|0.17021 Art|0.18085 formerly|0.19149 the|0.20213 Fairmount|0.21277 Park|0.2234 Art|0.23404 Association|0.24468 was|0.25532 created|0.26596 the|0.2766 first|0.28723 private|0.29787 association|0.30851 in|0.31915 the|0.32979 United|0.34043 States|0.35106 dedicated|0.3617 to|0.37234 integrating|0.38298 public|0.39362 art|0.40426 and|0.41489 urban|0.42553 planning|0.43617 97|0.44681 In|0.45745 1959|0.46809 lobbying|0.47872 by|0.48936 the|0.5 Artists|0.51064 Equity|0.52128 Association|0.53191 helped|0.54255 create|0.55319 the|0.56383 Percent|0.57447 for|0.58511 Art|0.59574 ordinance|0.60638 the|0.61702 first|0.62766 for|0.6383 a|0.64894 U|0.65957 S|0.67021 city|0.68085 98|0.69149 The|0.70213 program|0.71277 which|0.7234 has|0.73404 funded|0.74468 more|0.75532 than|0.76596 200|0.7766 pieces|0.78723 of|0.79787 public|0.80851 art|0.81915 is|0.82979 administered|0.84043 by|0.85106 the|0.8617 Philadelphia|0.87234 Office|0.88298 of|0.89362 Arts|0.90426 and|0.91489 Culture|0.92553 the|0.93617 city|0.94681 s|0.95745 art|0.96809 agency|0.97872 99|0.98936 |1"
		}
	}
}
