{
	"add": {
		"doc": {
			"id": "f237eb5630380172d5a0972b96a1b2ff230b64c3047c27843905e7beae4e3386",
			"url": "https://upload.wikimedia.org/wikipedia/commons/thumb/c/c8/RAMOS_pentagon_1998.jpg/220px-RAMOS_pentagon_1998.jpg",
			"previous": " ",
			"after": " The return of democracy and government reforms beginning in 1986 were hampered by national debt government corruption coup attempts disasters a persistent communist insurgency 103 and a military conflict with Moro separatists 104 Corazon Aquino s administration ended with the eruption of Mount Pinatubo in June 1991 105 106 withdrawal of U S forces due the rejection of the U S Bases Extension Treaty 107 108 and transfer of Clark Air Base in November 1991 and Subic Bay in December 1992 officially to the government ending the basing of American military forces in the country 109 110 ",
			"after_weights": " The|1 return|0.98969 of|0.97938 democracy|0.96907 and|0.95876 government|0.94845 reforms|0.93814 beginning|0.92784 in|0.91753 1986|0.90722 were|0.89691 hampered|0.8866 by|0.87629 national|0.86598 debt|0.85567 government|0.84536 corruption|0.83505 coup|0.82474 attempts|0.81443 disasters|0.80412 a|0.79381 persistent|0.78351 communist|0.7732 insurgency|0.76289 103|0.75258 and|0.74227 a|0.73196 military|0.72165 conflict|0.71134 with|0.70103 Moro|0.69072 separatists|0.68041 104|0.6701 Corazon|0.65979 Aquino|0.64948 s|0.63918 administration|0.62887 ended|0.61856 with|0.60825 the|0.59794 eruption|0.58763 of|0.57732 Mount|0.56701 Pinatubo|0.5567 in|0.54639 June|0.53608 1991|0.52577 105|0.51546 106|0.50515 withdrawal|0.49485 of|0.48454 U|0.47423 S|0.46392 forces|0.45361 due|0.4433 the|0.43299 rejection|0.42268 of|0.41237 the|0.40206 U|0.39175 S|0.38144 Bases|0.37113 Extension|0.36082 Treaty|0.35052 107|0.34021 108|0.3299 and|0.31959 transfer|0.30928 of|0.29897 Clark|0.28866 Air|0.27835 Base|0.26804 in|0.25773 November|0.24742 1991|0.23711 and|0.2268 Subic|0.21649 Bay|0.20619 in|0.19588 December|0.18557 1992|0.17526 officially|0.16495 to|0.15464 the|0.14433 government|0.13402 ending|0.12371 the|0.1134 basing|0.10309 of|0.092784 American|0.082474 military|0.072165 forces|0.061856 in|0.051546 the|0.041237 country|0.030928 109|0.020619 110|0.010309 |0",
			"previous_weights": " "
		}
	}
}
