{
	"add": {
		"doc": {
			"id": "0cfc06569b83701d01cbe28095793ee49429846298e80ee568dac258de879572",
			"url": "https://upload.wikimedia.org/math/8/0/4/804565c62408f4f87b51bd87357826d4.png",
				"previous": "We can also define a total order on Q. Let ∧ be the and-symbol and ∨ be the or-symbol. We say that [(m1,n1)] ≤ [(m2,n2)] if:",
				"after": "The integers may be considered to be rational numbers by the embedding that maps m to [(m,1)].",
			"color": "dim|0.37953 gray|0.37953 dim|0.37953 grey|0.37953 gray|0.28884 grey|0.28884 dark|0.1695 gray|0.1695 dark|0.1695 grey|0.1695 silver|0.076073 light|0.0383 gray|0.0383 light|0.0383 grey|0.0383 gainsboro|0.027452 white|0.0047623 smoke|0.0047623  "
		}
	}
}
