{
	"add": {
		"doc": {
			"id": "1c63bef07c2767e6aa2701544c33b663bdd3ef6a7bed3bb0693eec5c9aa356c4",
			"url": "https://upload.wikimedia.org/wikipedia/commons/thumb/4/49/Camp-Settlement.jpg/300px-Camp-Settlement.jpg",
			"previous": [],
				"after": "Falkland Islands English is mainly British in character. However, as a result of the isolation of the islands, the small population has developed and retains its own accent/dialect, which persists despite a large number of immigrants from the United Kingdom in recent years. In rural areas (i.e. anywhere outside Port Stanley), known as ‘Camp’ (from Spanish campo or ‘countryside’),[2] the Falkland accent tends to be stronger. The dialect has resemblances to Australian, New Zealand, West Country and Norfolk dialects of English, as well as Lowland Scots.",
			"color": "light|0.68339 steel|0.68339 blue|0.68339 silver|0.094395 dim|0.080617 gray|0.080617 dim|0.080617 grey|0.080617 gray|0.035549 grey|0.035549 light|0.025024 slate|0.025024 gray|0.025024 light|0.02094 gray|0.02094 light|0.02094 grey|0.02094 dark|0.017441 gray|0.017441 dark|0.017441 grey|0.017441 steel|0.01569 blue|0.01569  "
		}
	}
}
