{
	"add": {
		"doc": {
			"id": "205c4887500960054e68451d8774f2c04b5cd4089f5089035b0d59f4a5eb2b72",
			"url": "https://upload.wikimedia.org/wikipedia/commons/thumb/4/40/Adelie_Penguins_on_iceberg.jpg/220px-Adelie_Penguins_on_iceberg.jpg",
			"previous": [],
				"after": "The name Antarctica is the romanized version of the Greek compound word ἀνταρκτική (antarktiké), feminine of ἀνταρκτικός (antarktikos),[8] meaning \"opposite to the Arctic\", \"opposite to the north\".[9]",
			"color": "light|0.56717 steel|0.56717 blue|0.56717 light|0.11735 slate|0.11735 gray|0.11735 black|0.11067 gray|0.066762 grey|0.066762 dark|0.049393 gray|0.049393 dark|0.049393 grey|0.049393 dim|0.034765 gray|0.034765 dim|0.034765 grey|0.034765 slate|0.029669 gray|0.029669 silver|0.010373 lavender|0.0072039  "
		}
	}
}
