{
	"add": {
		"doc": {
			"id": "340dd4a19bc1334bd67f75b6f1e75758c4c7d88dce0ff963799e09bf85a82a01",
			"url": "https://upload.wikimedia.org/wikipedia/commons/thumb/8/88/Moselfraenkisch-Raps.ogg/220px--Moselfraenkisch-Raps.ogg.jpg",
			"previous": [],
				"after": "Hunsrückisch is a German dialect spoken in the Hunsrück region of Germany (Rhineland-Palatinate). This mountainous region of Germany has long been an exporter of emigrants to the United States, Canada, Brazil, Australia and other parts of the world.",
			"color": "gray|0.19662 grey|0.19662 dark|0.16712 salmon|0.16712 dim|0.092162 gray|0.092162 dim|0.092162 grey|0.092162 light|0.080139 salmon|0.080139 light|0.07812 gray|0.07812 light|0.07812 grey|0.07812 black|0.076208 firebrick|0.070277 antique|0.04304 white|0.04304 brown|0.037884 dark|0.036524 gray|0.036524 dark|0.036524 grey|0.036524 silver|0.029965 rosy|0.017665 brown|0.017665 gainsboro|0.015819 navajo|0.010696 white|0.010696 burly|0.010035 wood|0.010035 peach|0.0084069 puff|0.0084069  "
		}
	}
}
