{
	"add": {
		"doc": {
			"id": "35430b3a03bead9e1daaf978df19430d906ad838ae27256e6def3804478e5589",
			"url": "https://upload.wikimedia.org/wikipedia/commons/thumb/5/54/Lange-MigrantMother02.jpg/220px-Lange-MigrantMother02.jpg",
			"previous": [],
				"after": "The crisis was documented by photographers, musicians, and authors, many hired during the Great Depression by the federal government. For instance, the Farm Security Administration hired numerous photographers to document the crisis. Artists such as Dorothea Lange were aided by having salaried work during the Depression.[42] She captured what have become classic images of the dust storms and migrant families. Among her most well-known photographs is Destitute Pea Pickers in California. Mother of Seven Children,[42] which depicted a gaunt-looking woman, Florence Owens Thompson, holding three of her children. This picture expressed the struggles of people caught by the Dust Bowl and raised awareness in other parts of the country of its reach and human cost. Decades later, Thompson disliked the boundless circulation of the photo and resented the fact she did not receive any money from its broadcast. Thompson felt it gave her the perception as a Dust Bowl \"Okie.\"[43]",
			"color": " "
		}
	}
}
