{
	"add": {
		"doc": {
			"id": "68f885a15e5495c8c635b82975faa44e83e70a39ee3883ad9b21a189bce7ecfd",
			"url": "https://upload.wikimedia.org/wikipedia/commons/thumb/3/32/College_Football_CSU_AF.jpg/350px-College_Football_CSU_AF.jpg",
			"previous": [],
				"after": "College football is gridiron football played by teams of student athletes fielded by American universities, colleges, and military academies, or Canadian football played by teams of student athletes fielded by Canadian universities. It was through college football play that American football rules first gained popularity in the United States.",
			"color": "dark|0.12543 slate|0.12543 gray|0.12543 light|0.066133 cyan|0.066133 azure|0.061337 dark|0.057364 sea|0.057364 green|0.057364 mint|0.053452 cream|0.053452 alice|0.048898 blue|0.048898 light|0.04377 blue|0.04377 powder|0.040764 blue|0.040764 white|0.040044 smoke|0.040044 white|0.037442 honeydew|0.03711 light|0.035146 steel|0.035146 blue|0.035146 dim|0.033523 gray|0.033523 dim|0.033523 grey|0.033523 ghost|0.032715 white|0.032715 snow|0.031992 floral|0.027055 white|0.027055 slate|0.025831 gray|0.025831 light|0.025504 slate|0.025504 gray|0.025504 sea|0.018858 shell|0.018858 dark|0.015819 olive|0.015819 green|0.015819 ivory|0.013341 gray|0.01298 grey|0.01298 dark|0.012808 slate|0.012808 blue|0.012808 cadet|0.0095425 blue|0.0095425 pale|0.0095032 turquoise|0.0095032  "
		}
	}
}
