{
	"add": {
		"doc": {
			"id": "7c3422a73fcd178252a1147cdeffe8ae48859388e7e51fa89ddd844d16c873ea",
			"url": "https://upload.wikimedia.org/wikipedia/commons/thumb/4/4f/Reef_247.jpg/220px-Reef_247.jpg",
			"previous": [],
				"after": "The Caribbean region has seen a significant increase in human activity since the colonisation period. The sea is one of the largest oil production areas in the world, producing approximately 170 million tons per year.[22] The area also generates a large fishing industry for the surrounding countries, accounting for half a million metric tons of fish a year.[23]",
			"color": "dark|0.23797 slate|0.23797 gray|0.23797 sea|0.17795 green|0.17795 black|0.16858 medium|0.10856 sea|0.10856 green|0.10856 teal|0.091528 dark|0.053427 cyan|0.053427 turquoise|0.047751 light|0.04697 sea|0.04697 green|0.04697  "
		}
	}
}
