{
	"add": {
		"doc": {
			"id": "8cc86c7f35768dea57a5e3affec86c0c98aa34d1b0e3fcbece4ff729a1b14109",
			"url": "https://upload.wikimedia.org/math/2/c/1/2c1cf92adbf9ec05505e74de89b18002.png",
			"previous": [],
				"after": "In the base 10 numeral system, in almost universal use today for mathematical operations, the symbols for natural numbers are written using ten digits: 0, 1, 2, 3, 4, 5, 6, 7, 8, and 9. In this base 10 system, the rightmost digit of a natural number has a place value of 1, and every other digit has a place value ten times that of the place value of the digit to its right.",
			"color": "dark|0.28607 gray|0.28607 dark|0.28607 grey|0.28607 silver|0.19706 gray|0.18125 grey|0.18125 light|0.13546 gray|0.13546 light|0.13546 grey|0.13546 gainsboro|0.097429 dim|0.027063 gray|0.027063 dim|0.027063 grey|0.027063 white|0.020868 smoke|0.020868 linen|0.012965 lavender|0.0081686 blush|0.0081686 alice|0.0080126 blue|0.0080126 ghost|0.0077526 white|0.0077526 sea|0.0073515 shell|0.0073515 snow|0.007293 white|0.0029949  "
		}
	}
}
