{
	"add": {
		"doc": {
			"id": "94d2343707a597a3440d3a1ab15a75d9a4c8b972479055d5c241270332ffdae0",
			"url": "https://upload.wikimedia.org/wikipedia/commons/thumb/0/0c/OwatonnaBank.JPG/220px-OwatonnaBank.JPG",
			"previous": [],
				"after": "Saint Paul, located in east-central Minnesota along the banks of the Mississippi River, has been Minnesota's capital city since 1849, first as capital of the Territory of Minnesota, and then as state capital since 1858.",
			"color": "gray|0.33801 grey|0.33801 dark|0.27485 gray|0.27485 dark|0.27485 grey|0.27485 dim|0.18781 gray|0.18781 dim|0.18781 grey|0.18781 slate|0.042591 gray|0.042591 silver|0.034962 light|0.033769 slate|0.033769 gray|0.033769 rosy|0.020848 brown|0.020848 dark|0.019683 slate|0.019683 gray|0.019683 black|0.013774  "
		}
	}
}
